kdlearn/__init__.py
kdlearn/myfunctions.py
kdlearn-0.1.0.dist-info/METADATA
kdlearn-0.1.0.dist-info/WHEEL
kdlearn-0.1.0.dist-info/top_level.txt
kdlearn-0.1.0.dist-info/RECORD
