Metadata-Version: 2.1
Name: kdlearn
Version: 0.1.0
Summary: Package function For Ai and DATASCIENCE
Home-page: UNKNOWN
Author: DAVINCI AND FRIENDS
Author-email: UNKNOWN
License: MIT
Platform: UNKNOWN
